f3d/__init__.py
f3d/bin/f3d.dll
f3d/bin/vcruntime140.dll
f3d/bin/zlib.dll
f3d/py.typed
f3d/pyf3d.cp313-win_amd64.pyd
f3d/pyf3d.pyi
f3d/share/f3d/plugins/alembic.json
f3d/share/f3d/plugins/assimp.json
f3d/share/f3d/plugins/draco.json
f3d/share/f3d/plugins/hdf.json
f3d/share/f3d/plugins/native.json
f3d/share/f3d/plugins/occt.json
f3d-3.4.1.dist-info/METADATA
f3d-3.4.1.dist-info/WHEEL
f3d-3.4.1.dist-info/licenses/LICENSE.md
f3d-3.4.1.dist-info/licenses/THIRD_PARTY_LICENSES.md
f3d-3.4.1.dist-info/RECORD
