Metadata-Version: 2.1
Name: f3d
Version: 3.4.1
Summary: F3D, a fast and minimalist 3D viewer
Keywords: vtk,animations,fbx,step,stl,gltf,pbr,raytracing,rendering
Author: F3D-APP Foundation
Maintainer-Email: Michael Migliore <mcmigliore+pip@gmail.com>
License: BSD 3-Clause License
Classifier: Development Status :: 5 - Production/Stable
Classifier: License :: OSI Approved :: BSD License
Classifier: Operating System :: Microsoft :: Windows
Classifier: Operating System :: POSIX
Classifier: Operating System :: MacOS
Classifier: Programming Language :: C++
Classifier: Programming Language :: Python :: 3
Classifier: Topic :: Multimedia :: Graphics :: 3D Rendering
Classifier: Topic :: Multimedia :: Graphics :: Viewers
Classifier: Topic :: Scientific/Engineering :: Visualization
Project-URL: Homepage, https://f3d.app
Project-URL: Repository, https://github.com/f3d-app/f3d.git
Project-URL: Changelog, https://github.com/f3d-app/f3d/blob/master/doc/CHANGELOG.md
Requires-Python: >=3.10
